{
    "wallpaper": "/home/neil/downloads/1644267020179.png",
    "alpha": "100",
    "special": {
        "background": "#000000",
        "foreground": "#f4f4f4",
        "cursor": "#f4f4f4"
    },
    "colors": {
        "color0": "#000000",
        "color1": "#929292",
        "color2": "#B5B5B5",
        "color3": "#C9C9C9",
        "color4": "#D4D4D4",
        "color5": "#E9E9E9",
        "color6": "#F3F3F3",
        "color7": "#f4f4f4",
        "color8": "#aaaaaa",
        "color9": "#929292",
        "color10": "#B5B5B5",
        "color11": "#C9C9C9",
        "color12": "#D4D4D4",
        "color13": "#E9E9E9",
        "color14": "#F3F3F3",
        "color15": "#f4f4f4"
    }
}